[
    {
        "pk": 1, 
        "model": "analysis.beacons", 
        "fields": {
            "status": "1", 
            "verdat": 0, 
            "ninfom": null, 
            "elevat": "0E-11", 
            "datend": null, 
            "recdat": null, 
            "scamin": 260000, 
            "catspm": null, 
            "marsys": 0, 
            "catcam": 0, 
            "datsta": null, 
            "scamax": 0, 
            "beacon_typ": 5, 
            "ntxtds": null, 
            "condtn": 0, 
            "picrep": null, 
            "ruin": "I", 
            "rver": 1, 
            "persta": null, 
            "txtdsc": null, 
            "sorind": "US,US,graph,chart 18520", 
            "colpat": null, 
            "id_name": "FE0000000001", 
            "convis": 0, 
            "recind": null, 
            "natcon": null, 
            "height": "0E-11", 
            "name": null, 
            "catlam": 0, 
            "verlen": "0E-11", 
            "sordat": "19981107", 
            "geometry": "POINT (141084.9691000003367662 426853.1256000008434057)", 
            "colour": null, 
            "nobjnm": null, 
            "inform": "marker", 
            "lnam": "US028386586503417", 
            "veracc": "0E-11", 
            "grup": "002", 
            "perend": null, 
            "conrad": 0, 
            "bcnshp": 1
        }
    }, 
    {
        "pk": 2, 
        "model": "analysis.beacons", 
        "fields": {
            "status": "1", 
            "verdat": 0, 
            "ninfom": null, 
            "elevat": "0E-11", 
            "datend": null, 
            "recdat": null, 
            "scamin": 260000, 
            "catspm": "16", 
            "marsys": 0, 
            "catcam": 0, 
            "datsta": null, 
            "scamax": 0, 
            "beacon_typ": 5, 
            "ntxtds": null, 
            "condtn": 0, 
            "picrep": null, 
            "ruin": "I", 
            "rver": 1, 
            "persta": null, 
            "txtdsc": null, 
            "sorind": "US,US,reprt,13thCGD,LNM 15/99", 
            "colpat": null, 
            "id_name": "FE0000000003", 
            "convis": 0, 
            "recind": null, 
            "natcon": null, 
            "height": "0E-11", 
            "name": "Depoe Bay Entrance Range Front Light", 
            "catlam": 0, 
            "verlen": "0E-11", 
            "sordat": "19990413", 
            "geometry": "POINT (142547.3181999996304512 447580.3178000003099442)", 
            "colour": null, 
            "nobjnm": null, 
            "inform": null, 
            "lnam": "US028386586803417", 
            "veracc": "0E-11", 
            "grup": "002", 
            "perend": null, 
            "conrad": 0, 
            "bcnshp": 4
        }
    }, 
    {
        "pk": 3, 
        "model": "analysis.beacons", 
        "fields": {
            "status": "1", 
            "verdat": 0, 
            "ninfom": null, 
            "elevat": "0E-11", 
            "datend": null, 
            "recdat": null, 
            "scamin": 260000, 
            "catspm": "16", 
            "marsys": 0, 
            "catcam": 0, 
            "datsta": null, 
            "scamax": 0, 
            "beacon_typ": 5, 
            "ntxtds": null, 
            "condtn": 0, 
            "picrep": null, 
            "ruin": "I", 
            "rver": 1, 
            "persta": null, 
            "txtdsc": null, 
            "sorind": "US,US,reprt,13thCGD,LNM 15/99", 
            "colpat": null, 
            "id_name": "FE0000000006", 
            "convis": 0, 
            "recind": null, 
            "natcon": null, 
            "height": "0E-11", 
            "name": "Depoe Bay Entrance Range Rear Light", 
            "catlam": 0, 
            "verlen": "0E-11", 
            "sordat": "19990413", 
            "geometry": "POINT (142562.8489999994635582 447578.9503000006079674)", 
            "colour": null, 
            "nobjnm": null, 
            "inform": null, 
            "lnam": "US028386587203417", 
            "veracc": "0E-11", 
            "grup": "002", 
            "perend": null, 
            "conrad": 0, 
            "bcnshp": 4
        }
    }, 
    {
        "pk": 4, 
        "model": "analysis.beacons", 
        "fields": {
            "status": "1", 
            "verdat": 0, 
            "ninfom": null, 
            "elevat": "0E-11", 
            "datend": null, 
            "recdat": null, 
            "scamin": 260000, 
            "catspm": "27", 
            "marsys": 0, 
            "catcam": 0, 
            "datsta": null, 
            "scamax": 0, 
            "beacon_typ": 5, 
            "ntxtds": null, 
            "condtn": 0, 
            "picrep": null, 
            "ruin": "I", 
            "rver": 1, 
            "persta": null, 
            "txtdsc": null, 
            "sorind": "US,US,reprt,13thCGD,ATONIS", 
            "colpat": null, 
            "id_name": "FE0000000009", 
            "convis": 0, 
            "recind": null, 
            "natcon": null, 
            "height": "0E-11", 
            "name": "Tillamook Bay North Jetty Light 3", 
            "catlam": 0, 
            "verlen": "0E-11", 
            "sordat": "20041220", 
            "geometry": "POINT (157578.7031999994069338 531269.6932999994605780)", 
            "colour": "4", 
            "nobjnm": null, 
            "inform": "Due to weather conditions the dayboards have been permanently removed from this aid.", 
            "lnam": "US028386587703417", 
            "veracc": "0E-11", 
            "grup": "002", 
            "perend": null, 
            "conrad": 0, 
            "bcnshp": 5
        }
    }, 
    {
        "pk": 5, 
        "model": "analysis.beacons", 
        "fields": {
            "status": "1", 
            "verdat": 0, 
            "ninfom": null, 
            "elevat": "0E-11", 
            "datend": null, 
            "recdat": null, 
            "scamin": 260000, 
            "catspm": "27", 
            "marsys": 0, 
            "catcam": 0, 
            "datsta": null, 
            "scamax": 0, 
            "beacon_typ": 5, 
            "ntxtds": null, 
            "condtn": 0, 
            "picrep": null, 
            "ruin": "I", 
            "rver": 1, 
            "persta": null, 
            "txtdsc": null, 
            "sorind": "US,US,reprt,13thCGD,LNM 19/06", 
            "colpat": null, 
            "id_name": "FE0000000012", 
            "convis": 0, 
            "recind": null, 
            "natcon": null, 
            "height": "0E-11", 
            "name": "Tillamook Bay Entrance Direction Light", 
            "catlam": 0, 
            "verlen": "0E-11", 
            "sordat": "20060509", 
            "geometry": "POINT (159334.8279999997466803 530852.1066999994218349)", 
            "colour": null, 
            "nobjnm": null, 
            "inform": null, 
            "lnam": "US028386588203417", 
            "veracc": "0E-11", 
            "grup": "002", 
            "perend": null, 
            "conrad": 0, 
            "bcnshp": 4
        }
    }, 
    {
        "pk": 6, 
        "model": "analysis.beacons", 
        "fields": {
            "status": "1", 
            "verdat": 0, 
            "ninfom": null, 
            "elevat": "0E-11", 
            "datend": null, 
            "recdat": null, 
            "scamin": 260000, 
            "catspm": "27", 
            "marsys": 0, 
            "catcam": 0, 
            "datsta": null, 
            "scamax": 0, 
            "beacon_typ": 5, 
            "ntxtds": null, 
            "condtn": 0, 
            "picrep": null, 
            "ruin": "I", 
            "rver": 1, 
            "persta": null, 
            "txtdsc": null, 
            "sorind": "US,US,reprt,13thCGD,ATONIS", 
            "colpat": "1", 
            "id_name": "FE0000000016", 
            "convis": 1, 
            "recind": null, 
            "natcon": null, 
            "height": "0E-11", 
            "name": "Cape Disappointment Light", 
            "catlam": 0, 
            "verlen": "16.1000000000", 
            "sordat": "20050503", 
            "geometry": "POINT (157605.3640999998897314 610021.0210999995470047)", 
            "colour": "1,2,1", 
            "nobjnm": null, 
            "inform": "Conical", 
            "lnam": "US028386588603417", 
            "veracc": "0E-11", 
            "grup": "002", 
            "perend": null, 
            "conrad": 0, 
            "bcnshp": 3
        }
    }, 
    {
        "pk": 7, 
        "model": "analysis.beacons", 
        "fields": {
            "status": "1", 
            "verdat": 0, 
            "ninfom": null, 
            "elevat": "0E-11", 
            "datend": null, 
            "recdat": null, 
            "scamin": 260000, 
            "catspm": "16", 
            "marsys": 0, 
            "catcam": 0, 
            "datsta": null, 
            "scamax": 0, 
            "beacon_typ": 5, 
            "ntxtds": null, 
            "condtn": 0, 
            "picrep": null, 
            "ruin": "I", 
            "rver": 1, 
            "persta": null, 
            "txtdsc": null, 
            "sorind": "US,US,graph,chart 18520", 
            "colpat": null, 
            "id_name": "FE0000000021", 
            "convis": 0, 
            "recind": null, 
            "natcon": null, 
            "height": "0E-11", 
            "name": "Columbia River Entrance Range Front Light", 
            "catlam": 0, 
            "verlen": "0E-11", 
            "sordat": "19981107", 
            "geometry": "POINT (157659.6087999995797873 610020.8696999996900558)", 
            "colour": null, 
            "nobjnm": null, 
            "inform": null, 
            "lnam": "US028386589103417", 
            "veracc": "0E-11", 
            "grup": "002", 
            "perend": null, 
            "conrad": 0, 
            "bcnshp": 4
        }
    }, 
    {
        "pk": 8, 
        "model": "analysis.beacons", 
        "fields": {
            "status": "1", 
            "verdat": 0, 
            "ninfom": null, 
            "elevat": "0E-11", 
            "datend": null, 
            "recdat": null, 
            "scamin": 260000, 
            "catspm": "16", 
            "marsys": 0, 
            "catcam": 0, 
            "datsta": null, 
            "scamax": 0, 
            "beacon_typ": 5, 
            "ntxtds": null, 
            "condtn": 0, 
            "picrep": null, 
            "ruin": "I", 
            "rver": 1, 
            "persta": null, 
            "txtdsc": null, 
            "sorind": "US,US,graph,chart 18520", 
            "colpat": null, 
            "id_name": "FE0000000024", 
            "convis": 0, 
            "recind": null, 
            "natcon": null, 
            "height": "0E-11", 
            "name": "Columbia River Entrance Range Rear Light", 
            "catlam": 0, 
            "verlen": "0E-11", 
            "sordat": "19981107", 
            "geometry": "POINT (158109.7764999996870756 610386.9521999992430210)", 
            "colour": null, 
            "nobjnm": null, 
            "inform": null, 
            "lnam": "US028386589603417", 
            "veracc": "0E-11", 
            "grup": "002", 
            "perend": null, 
            "conrad": 0, 
            "bcnshp": 4
        }
    }, 
    {
        "pk": 9, 
        "model": "analysis.beacons", 
        "fields": {
            "status": "1", 
            "verdat": 0, 
            "ninfom": null, 
            "elevat": "0E-11", 
            "datend": null, 
            "recdat": null, 
            "scamin": 260000, 
            "catspm": "16", 
            "marsys": 0, 
            "catcam": 0, 
            "datsta": null, 
            "scamax": 0, 
            "beacon_typ": 5, 
            "ntxtds": null, 
            "condtn": 0, 
            "picrep": null, 
            "ruin": "I", 
            "rver": 1, 
            "persta": null, 
            "txtdsc": null, 
            "sorind": "US,US,reprt,13thCGD,LNM 11/03", 
            "colpat": null, 
            "id_name": "FE0000000030", 
            "convis": 0, 
            "recind": null, 
            "natcon": null, 
            "height": "0E-11", 
            "name": "Sand Island Range Front Light", 
            "catlam": 0, 
            "verlen": "0E-11", 
            "sordat": "20030318", 
            "geometry": "POINT (162060.3859999999403954 608519.4122000001370907)", 
            "colour": null, 
            "nobjnm": null, 
            "inform": "On Pile Structure", 
            "lnam": "US028386590003417", 
            "veracc": "0E-11", 
            "grup": "002", 
            "perend": null, 
            "conrad": 0, 
            "bcnshp": 4
        }
    }, 
    {
        "pk": 10, 
        "model": "analysis.beacons", 
        "fields": {
            "status": "1", 
            "verdat": 0, 
            "ninfom": null, 
            "elevat": "0E-11", 
            "datend": null, 
            "recdat": null, 
            "scamin": 260000, 
            "catspm": "16", 
            "marsys": 0, 
            "catcam": 0, 
            "datsta": null, 
            "scamax": 0, 
            "beacon_typ": 5, 
            "ntxtds": null, 
            "condtn": 0, 
            "picrep": null, 
            "ruin": "I", 
            "rver": 1, 
            "persta": null, 
            "txtdsc": null, 
            "sorind": "US,US,reprt,13thCGD,LNM 11/03", 
            "colpat": null, 
            "id_name": "FE0000000033", 
            "convis": 0, 
            "recind": null, 
            "natcon": null, 
            "height": "0E-11", 
            "name": "Sand Island Range Rear Light", 
            "catlam": 0, 
            "verlen": "0E-11", 
            "sordat": "20030318", 
            "geometry": "POINT (162978.0814999993890524 608600.7795000001788139)", 
            "colour": null, 
            "nobjnm": null, 
            "inform": "On Pile Structure.  914.4 meters/ 1000 yards 80 degrees from front light", 
            "lnam": "US028386590503417", 
            "veracc": "0E-11", 
            "grup": "002", 
            "perend": null, 
            "conrad": 0, 
            "bcnshp": 4
        }
    }, 
    {
        "pk": 11, 
        "model": "analysis.beacons", 
        "fields": {
            "status": "1", 
            "verdat": 0, 
            "ninfom": null, 
            "elevat": "0E-11", 
            "datend": null, 
            "recdat": null, 
            "scamin": 260000, 
            "catspm": "41", 
            "marsys": 0, 
            "catcam": 0, 
            "datsta": null, 
            "scamax": 0, 
            "beacon_typ": 5, 
            "ntxtds": null, 
            "condtn": 0, 
            "picrep": null, 
            "ruin": "I", 
            "rver": 1, 
            "persta": null, 
            "txtdsc": null, 
            "sorind": "US,US,graph,chart 18580", 
            "colpat": null, 
            "id_name": "FE0000000008", 
            "convis": 0, 
            "recind": null, 
            "natcon": null, 
            "height": "0E-11", 
            "name": null, 
            "catlam": 0, 
            "verlen": "0E-11", 
            "sordat": "20010915", 
            "geometry": "POINT (119200.6353999990969896 319657.6782000008970499)", 
            "colour": "11", 
            "nobjnm": null, 
            "inform": null, 
            "lnam": "US014599764903305", 
            "veracc": "0E-11", 
            "grup": "002", 
            "perend": null, 
            "conrad": 0, 
            "bcnshp": 0
        }
    }, 
    {
        "pk": 12, 
        "model": "analysis.beacons", 
        "fields": {
            "status": "1", 
            "verdat": 0, 
            "ninfom": null, 
            "elevat": "0E-11", 
            "datend": null, 
            "recdat": null, 
            "scamin": 260000, 
            "catspm": "41", 
            "marsys": 0, 
            "catcam": 0, 
            "datsta": null, 
            "scamax": 0, 
            "beacon_typ": 5, 
            "ntxtds": null, 
            "condtn": 0, 
            "picrep": null, 
            "ruin": "I", 
            "rver": 1, 
            "persta": null, 
            "txtdsc": null, 
            "sorind": "US,US,graph,chart 18580", 
            "colpat": null, 
            "id_name": "FE0000000009", 
            "convis": 0, 
            "recind": null, 
            "natcon": null, 
            "height": "0E-11", 
            "name": null, 
            "catlam": 0, 
            "verlen": "0E-11", 
            "sordat": "20010915", 
            "geometry": "POINT (119644.1839000005275011 319437.3978000003844500)", 
            "colour": "11", 
            "nobjnm": null, 
            "inform": null, 
            "lnam": "US014599764803305", 
            "veracc": "0E-11", 
            "grup": "002", 
            "perend": null, 
            "conrad": 0, 
            "bcnshp": 0
        }
    }, 
    {
        "pk": 13, 
        "model": "analysis.beacons", 
        "fields": {
            "status": "1", 
            "verdat": 0, 
            "ninfom": null, 
            "elevat": "0E-11", 
            "datend": null, 
            "recdat": null, 
            "scamin": 260000, 
            "catspm": "41", 
            "marsys": 0, 
            "catcam": 0, 
            "datsta": null, 
            "scamax": 0, 
            "beacon_typ": 5, 
            "ntxtds": null, 
            "condtn": 0, 
            "picrep": null, 
            "ruin": "I", 
            "rver": 1, 
            "persta": null, 
            "txtdsc": null, 
            "sorind": "US,US,graph,chart 18580", 
            "colpat": null, 
            "id_name": "FE0000000012", 
            "convis": 0, 
            "recind": null, 
            "natcon": null, 
            "height": "0E-11", 
            "name": null, 
            "catlam": 0, 
            "verlen": "0E-11", 
            "sordat": "20010915", 
            "geometry": "POINT (119572.1098999995738268 321121.7017999999225140)", 
            "colour": "11", 
            "nobjnm": null, 
            "inform": null, 
            "lnam": "US014599765103305", 
            "veracc": "0E-11", 
            "grup": "002", 
            "perend": null, 
            "conrad": 0, 
            "bcnshp": 0
        }
    }, 
    {
        "pk": 14, 
        "model": "analysis.beacons", 
        "fields": {
            "status": "1", 
            "verdat": 0, 
            "ninfom": null, 
            "elevat": "0E-11", 
            "datend": null, 
            "recdat": null, 
            "scamin": 260000, 
            "catspm": "41", 
            "marsys": 0, 
            "catcam": 0, 
            "datsta": null, 
            "scamax": 0, 
            "beacon_typ": 5, 
            "ntxtds": null, 
            "condtn": 0, 
            "picrep": null, 
            "ruin": "I", 
            "rver": 1, 
            "persta": null, 
            "txtdsc": null, 
            "sorind": "US,US,graph,chart 18580", 
            "colpat": null, 
            "id_name": "FE0000000013", 
            "convis": 0, 
            "recind": null, 
            "natcon": null, 
            "height": "0E-11", 
            "name": null, 
            "catlam": 0, 
            "verlen": "0E-11", 
            "sordat": "20010915", 
            "geometry": "POINT (120031.0800999999046326 321350.4035000000149012)", 
            "colour": "11", 
            "nobjnm": null, 
            "inform": null, 
            "lnam": "US014599765303305", 
            "veracc": "0E-11", 
            "grup": "002", 
            "perend": null, 
            "conrad": 0, 
            "bcnshp": 0
        }
    }, 
    {
        "pk": 15, 
        "model": "analysis.beacons", 
        "fields": {
            "status": "1", 
            "verdat": 0, 
            "ninfom": null, 
            "elevat": "0E-11", 
            "datend": null, 
            "recdat": null, 
            "scamin": 260000, 
            "catspm": "27", 
            "marsys": 0, 
            "catcam": 0, 
            "datsta": null, 
            "scamax": 0, 
            "beacon_typ": 5, 
            "ntxtds": null, 
            "condtn": 0, 
            "picrep": null, 
            "ruin": "I", 
            "rver": 1, 
            "persta": null, 
            "txtdsc": null, 
            "sorind": "US,US,graph,chart 18580", 
            "colpat": null, 
            "id_name": "FE0000000001", 
            "convis": 0, 
            "recind": null, 
            "natcon": null, 
            "height": "0E-11", 
            "name": "Coquille River South Jetty Light 8", 
            "catlam": 0, 
            "verlen": "0E-11", 
            "sordat": "20010915", 
            "geometry": "POINT (96142.3753999993205070 263561.5196000002324581)", 
            "colour": null, 
            "nobjnm": null, 
            "inform": null, 
            "lnam": "US014600174603305", 
            "veracc": "0E-11", 
            "grup": "002", 
            "perend": null, 
            "conrad": 0, 
            "bcnshp": 0
        }
    }, 
    {
        "pk": 16, 
        "model": "analysis.beacons", 
        "fields": {
            "status": "1", 
            "verdat": 0, 
            "ninfom": null, 
            "elevat": "0E-11", 
            "datend": null, 
            "recdat": null, 
            "scamin": 260000, 
            "catspm": "27", 
            "marsys": 0, 
            "catcam": 0, 
            "datsta": null, 
            "scamax": 0, 
            "beacon_typ": 5, 
            "ntxtds": null, 
            "condtn": 0, 
            "picrep": null, 
            "ruin": "I", 
            "rver": 1, 
            "persta": null, 
            "txtdsc": null, 
            "sorind": "US,US,reprt,13thCGD,ATONIS", 
            "colpat": null, 
            "id_name": "FE0000000005", 
            "convis": 0, 
            "recind": null, 
            "natcon": null, 
            "height": "0E-11", 
            "name": "Coos Bay North Jetty Light 3A", 
            "catlam": 0, 
            "verlen": "0E-11", 
            "sordat": "20041129", 
            "geometry": "POINT (105610.3892000000923872 288933.7886999994516373)", 
            "colour": "4", 
            "nobjnm": null, 
            "inform": "Due to weather conditions, the dayboards have been removed from this aid.", 
            "lnam": "US014600175103305", 
            "veracc": "0E-11", 
            "grup": "002", 
            "perend": null, 
            "conrad": 0, 
            "bcnshp": 5
        }
    }, 
    {
        "pk": 17, 
        "model": "analysis.beacons", 
        "fields": {
            "status": "1", 
            "verdat": 0, 
            "ninfom": null, 
            "elevat": "0E-11", 
            "datend": null, 
            "recdat": null, 
            "scamin": 260000, 
            "catspm": "27", 
            "marsys": 0, 
            "catcam": 0, 
            "datsta": null, 
            "scamax": 0, 
            "beacon_typ": 5, 
            "ntxtds": null, 
            "condtn": 0, 
            "picrep": null, 
            "ruin": "I", 
            "rver": 1, 
            "persta": null, 
            "txtdsc": null, 
            "sorind": "US,US,reprt,13thCGD,ATONIS", 
            "colpat": null, 
            "id_name": "FE0000000016", 
            "convis": 0, 
            "recind": null, 
            "natcon": null, 
            "height": "0E-11", 
            "name": "Siuslaw River North Jetty Light 3", 
            "catlam": 0, 
            "verlen": "0E-11", 
            "sordat": "20041220", 
            "geometry": "POINT (128108.9881999995559454 360640.5690000001341105)", 
            "colour": "4", 
            "nobjnm": null, 
            "inform": "Due to weather conditions, the dayboards have been permanently removed from this aid.", 
            "lnam": "US014600175603305", 
            "veracc": "0E-11", 
            "grup": "002", 
            "perend": null, 
            "conrad": 0, 
            "bcnshp": 5
        }
    }, 
    {
        "pk": 18, 
        "model": "analysis.beacons", 
        "fields": {
            "status": "1", 
            "verdat": 0, 
            "ninfom": null, 
            "elevat": "0E-11", 
            "datend": null, 
            "recdat": null, 
            "scamin": 260000, 
            "catspm": "16", 
            "marsys": 0, 
            "catcam": 0, 
            "datsta": null, 
            "scamax": 0, 
            "beacon_typ": 5, 
            "ntxtds": null, 
            "condtn": 0, 
            "picrep": null, 
            "ruin": "I", 
            "rver": 1, 
            "persta": null, 
            "txtdsc": null, 
            "sorind": "US,US,graph,chart 18580", 
            "colpat": null, 
            "id_name": "FE0000000021", 
            "convis": 0, 
            "recind": null, 
            "natcon": null, 
            "height": "0E-11", 
            "name": "Siuslaw River Entrance Range Front Light", 
            "catlam": 0, 
            "verlen": "0E-11", 
            "sordat": "20010915", 
            "geometry": "POINT (129356.6585000008344650 360317.3224999997764826)", 
            "colour": null, 
            "nobjnm": null, 
            "inform": null, 
            "lnam": "US014600176003305", 
            "veracc": "0E-11", 
            "grup": "002", 
            "perend": null, 
            "conrad": 0, 
            "bcnshp": 4
        }
    }, 
    {
        "pk": 19, 
        "model": "analysis.beacons", 
        "fields": {
            "status": "1", 
            "verdat": 0, 
            "ninfom": null, 
            "elevat": "0E-11", 
            "datend": null, 
            "recdat": null, 
            "scamin": 260000, 
            "catspm": "16", 
            "marsys": 0, 
            "catcam": 0, 
            "datsta": null, 
            "scamax": 0, 
            "beacon_typ": 5, 
            "ntxtds": null, 
            "condtn": 0, 
            "picrep": null, 
            "ruin": "I", 
            "rver": 1, 
            "persta": null, 
            "txtdsc": null, 
            "sorind": "US,US,reprt,13thCGD,ATONIS", 
            "colpat": null, 
            "id_name": "FE0000000024", 
            "convis": 0, 
            "recind": null, 
            "natcon": null, 
            "height": "0E-11", 
            "name": "Siuslaw River Entrance Range Rear Light", 
            "catlam": 0, 
            "verlen": "0E-11", 
            "sordat": "20040824", 
            "geometry": "POINT (129615.3824000004678965 360257.3587999995797873)", 
            "colour": null, 
            "nobjnm": null, 
            "inform": null, 
            "lnam": "US014600176503305", 
            "veracc": "0E-11", 
            "grup": "002", 
            "perend": null, 
            "conrad": 0, 
            "bcnshp": 4
        }
    }, 
    {
        "pk": 20, 
        "model": "analysis.beacons", 
        "fields": {
            "status": "1", 
            "verdat": 0, 
            "ninfom": null, 
            "elevat": "0E-11", 
            "datend": null, 
            "recdat": null, 
            "scamin": 260000, 
            "catspm": "27", 
            "marsys": 0, 
            "catcam": 0, 
            "datsta": null, 
            "scamax": 0, 
            "beacon_typ": 5, 
            "ntxtds": null, 
            "condtn": 0, 
            "picrep": null, 
            "ruin": "I", 
            "rver": 1, 
            "persta": null, 
            "txtdsc": null, 
            "sorind": "US,US,reprt,13thCGD,ATONIS", 
            "colpat": null, 
            "id_name": "FE0000000028", 
            "convis": 0, 
            "recind": null, 
            "natcon": null, 
            "height": "0E-11", 
            "name": "Yaquina Bay South Jetty Light 4", 
            "catlam": 0, 
            "verlen": "0E-11", 
            "sordat": "20041129", 
            "geometry": "POINT (139219.6237000003457069 425547.0199999995529652)", 
            "colour": "3", 
            "nobjnm": null, 
            "inform": "Due to heavy weather conditions, the dayboards have been permanently removed from this aid.", 
            "lnam": "US014600177003305", 
            "veracc": "0E-11", 
            "grup": "002", 
            "perend": null, 
            "conrad": 0, 
            "bcnshp": 5
        }
    }, 
    {
        "pk": 21, 
        "model": "analysis.beacons", 
        "fields": {
            "status": "1", 
            "verdat": 0, 
            "ninfom": null, 
            "elevat": "0E-11", 
            "datend": null, 
            "recdat": null, 
            "scamin": 260000, 
            "catspm": null, 
            "marsys": 0, 
            "catcam": 0, 
            "datsta": null, 
            "scamax": 0, 
            "beacon_typ": 3, 
            "ntxtds": null, 
            "condtn": 0, 
            "picrep": null, 
            "ruin": "I", 
            "rver": 1, 
            "persta": null, 
            "txtdsc": null, 
            "sorind": "US,US,reprt,13thCGD,LNM 26/02", 
            "colpat": null, 
            "id_name": "FE0000000004", 
            "convis": 0, 
            "recind": null, 
            "natcon": null, 
            "height": "0E-11", 
            "name": "Chetco River Entrance Light 5", 
            "catlam": 1, 
            "verlen": "0E-11", 
            "sordat": "20020625", 
            "geometry": "POINT (98215.6688999999314547 142939.3248999994248152)", 
            "colour": "4", 
            "nobjnm": null, 
            "inform": "Due to weather conditions the dayboards have been removed from this aid.", 
            "lnam": "US018573150103369", 
            "veracc": "0E-11", 
            "grup": "002", 
            "perend": null, 
            "conrad": 0, 
            "bcnshp": 5
        }
    }, 
    {
        "pk": 22, 
        "model": "analysis.beacons", 
        "fields": {
            "status": "1", 
            "verdat": 0, 
            "ninfom": null, 
            "elevat": "0E-11", 
            "datend": null, 
            "recdat": null, 
            "scamin": 260000, 
            "catspm": "27", 
            "marsys": 0, 
            "catcam": 0, 
            "datsta": null, 
            "scamax": 0, 
            "beacon_typ": 5, 
            "ntxtds": null, 
            "condtn": 0, 
            "picrep": null, 
            "ruin": "I", 
            "rver": 1, 
            "persta": null, 
            "txtdsc": null, 
            "sorind": "US,US,graph,chart 18600", 
            "colpat": null, 
            "id_name": "FE0000000006", 
            "convis": 0, 
            "recind": null, 
            "natcon": null, 
            "height": "0E-11", 
            "name": "Reading Rocks Light", 
            "catlam": 0, 
            "verlen": "0E-11", 
            "sordat": "20020126", 
            "geometry": "POINT (99014.2348999995738268 64601.2360999993979931)", 
            "colour": null, 
            "nobjnm": null, 
            "inform": null, 
            "lnam": "US018573150403369", 
            "veracc": "0E-11", 
            "grup": "002", 
            "perend": null, 
            "conrad": 0, 
            "bcnshp": 0
        }
    }, 
    {
        "pk": 23, 
        "model": "analysis.beacons", 
        "fields": {
            "status": "8", 
            "verdat": 0, 
            "ninfom": null, 
            "elevat": "0E-11", 
            "datend": null, 
            "recdat": null, 
            "scamin": 260000, 
            "catspm": "27", 
            "marsys": 0, 
            "catcam": 0, 
            "datsta": null, 
            "scamax": 0, 
            "beacon_typ": 5, 
            "ntxtds": null, 
            "condtn": 0, 
            "picrep": null, 
            "ruin": "I", 
            "rver": 1, 
            "persta": null, 
            "txtdsc": null, 
            "sorind": "US,US,graph,chart 18600", 
            "colpat": null, 
            "id_name": "FE0000000009", 
            "convis": 0, 
            "recind": null, 
            "natcon": null, 
            "height": "0E-11", 
            "name": "Battery Point Light", 
            "catlam": 0, 
            "verlen": "0E-11", 
            "sordat": "20020126", 
            "geometry": "POINT (101015.9769999999552965 109438.2112000007182360)", 
            "colour": "1", 
            "nobjnm": null, 
            "inform": "Two story structure.", 
            "lnam": "US018573151303369", 
            "veracc": "0E-11", 
            "grup": "002", 
            "perend": null, 
            "conrad": 0, 
            "bcnshp": 0
        }
    }, 
    {
        "pk": 24, 
        "model": "analysis.beacons", 
        "fields": {
            "status": "1", 
            "verdat": 0, 
            "ninfom": null, 
            "elevat": "0E-11", 
            "datend": null, 
            "recdat": null, 
            "scamin": 260000, 
            "catspm": "27", 
            "marsys": 0, 
            "catcam": 0, 
            "datsta": null, 
            "scamax": 0, 
            "beacon_typ": 5, 
            "ntxtds": null, 
            "condtn": 0, 
            "picrep": null, 
            "ruin": "I", 
            "rver": 1, 
            "persta": null, 
            "txtdsc": null, 
            "sorind": "US,US,reprt,13thCGD,ATONIS", 
            "colpat": null, 
            "id_name": "FE0000000011", 
            "convis": 0, 
            "recind": null, 
            "natcon": null, 
            "height": "0E-11", 
            "name": "Crescent City Entrance Light", 
            "catlam": 0, 
            "verlen": "0E-11", 
            "sordat": "20050316", 
            "geometry": "POINT (101888.6473999992012978 108422.1714999992400408)", 
            "colour": null, 
            "nobjnm": null, 
            "inform": null, 
            "lnam": "US018573150903369", 
            "veracc": "0E-11", 
            "grup": "002", 
            "perend": null, 
            "conrad": 0, 
            "bcnshp": 5
        }
    }, 
    {
        "pk": 25, 
        "model": "analysis.beacons", 
        "fields": {
            "status": "1", 
            "verdat": 0, 
            "ninfom": null, 
            "elevat": "0E-11", 
            "datend": null, 
            "recdat": null, 
            "scamin": 260000, 
            "catspm": "27", 
            "marsys": 0, 
            "catcam": 0, 
            "datsta": null, 
            "scamax": 0, 
            "beacon_typ": 5, 
            "ntxtds": null, 
            "condtn": 0, 
            "picrep": null, 
            "ruin": "I", 
            "rver": 1, 
            "persta": null, 
            "txtdsc": null, 
            "sorind": "US,US,reprt,13thCGD,ATONIS", 
            "colpat": null, 
            "id_name": "FE0000000014", 
            "convis": 0, 
            "recind": null, 
            "natcon": null, 
            "height": "0E-11", 
            "name": "Rogue River North Jetty Light 3", 
            "catlam": 0, 
            "verlen": "0E-11", 
            "sordat": "20050503", 
            "geometry": "POINT (88829.7145000007003546 185854.7397000007331371)", 
            "colour": null, 
            "nobjnm": null, 
            "inform": null, 
            "lnam": "US018573151703369", 
            "veracc": "0E-11", 
            "grup": "002", 
            "perend": null, 
            "conrad": 0, 
            "bcnshp": 4
        }
    }
]